review_tools/__init__.py
review_tools/__main__.py
review_tools/cli.py
review_tools/diff_app.py
review_tools/summary_app.py
scripts/__init__.py
scripts/__main__.py
scripts/cli.py
scripts/evaluate.py
scripts/evaluate_metrics/__init__.py
scripts/evaluate_metrics/base_metric.py
scripts/evaluate_metrics/builtin_metrics.py
scripts/evaluate_metrics/code_metrics.py
scripts/evaluate_metrics/prompt_metrics.py
scripts/generate.py
scripts/service_setup.py
scripts/tests/test_evaluate.py
scripts/tests/test_evaluate_metrics.py
ai_rag_chat_evaluator-0.2.0.dist-info/LICENSE.md
ai_rag_chat_evaluator-0.2.0.dist-info/METADATA
ai_rag_chat_evaluator-0.2.0.dist-info/WHEEL
ai_rag_chat_evaluator-0.2.0.dist-info/RECORD
