Metadata-Version: 2.1
Name: ai-rag-chat-evaluator
Version: 0.2.0
Summary: Tools for evaluation of RAG Chat Apps using Azure AI Evaluate SDK and OpenAI
Home-page: https://github.com/Azure-Samples/ai-rag-chat-evaluator
License: MIT
Keywords: ai,rag,chat,azure,sdk,openai
Author: Pamela Fox
Author-email: pamelafox@fosstodon.org
Maintainer: Oleksis Fraga
Maintainer-email: oleksis.fraga@gmail.com
Requires-Python: >=3.10,<4.0
Classifier: License :: OSI Approved :: MIT License
Classifier: Programming Language :: Python :: 3
Classifier: Programming Language :: Python :: 3.10
Classifier: Programming Language :: Python :: 3.11
Classifier: Programming Language :: Python :: 3.12
Classifier: Topic :: Software Development :: Build Tools
Classifier: Topic :: Software Development :: Libraries :: Python Modules
Requires-Dist: azure-ai-generative[evaluate] (==1.0.0b7)
Requires-Dist: azure-search-documents
Requires-Dist: openai (>=1.0.0)
Requires-Dist: pandas
Requires-Dist: python-dotenv
Requires-Dist: requests
Requires-Dist: textual
Requires-Dist: typer
Project-URL: Repository, https://github.com/Azure-Samples/ai-rag-chat-evaluator
